<?xml version="1.0" encoding="UTF-8"?>
<features name="camel-mashup" xmlns="http://karaf.apache.org/xmlns/features/v1.0.0">

    <feature name="camel-mashup" version="${project.version}" resolver="(obr)">
        <feature version="[2.8,3)">camel-core</feature>
        <bundle dependency="true">mvn:commons-beanutils/commons-beanutils-core/${commons-beanutils.version}</bundle>
        <bundle dependency="true">mvn:org.apache.commons/commons-digester3/${commons-digester.version}</bundle>
        <bundle dependency="true">mvn:org.apache.httpcomponents/httpclient-osgi/${httpclient.version}</bundle>
        <bundle dependency="true">mvn:org.jsoup/jsoup/${jsoup.version}</bundle>
        <bundle>mvn:org.apache.camel.processor/camel-mashup/${project.version}</bundle>
    </feature>

</features>